[
{"description_or_mfg_pn": "SFS5-L-DC24V-D", "supplier_links": {}, "item": null},
{"description_or_mfg_pn": "3240294", "supplier_links": {"digikey.sg": ["https://www.digikey.sg/en/products/detail/phoenix-contact/3240294/2525016"], "sg.rs-online.com": ["https://sg.rs-online.com/web/p/cable-trunkings/8045815"]}, "item": null},
{"description_or_mfg_pn": "RJ2S-CLD-D24", "supplier_links": {"sg.element14.com": ["https://sg.element14.com/idec/rj2s-cld-d24/relay-dpdt-250vac-30vdc-8a/dp/1638022", "https://sg.element14.com/idec/rj2s-cld-d24/power-relay-dpdt-24vdc-8a-socket/dp/3765901"], "digikey.sg": ["https://www.digikey.sg/en/products/detail/idec/RJ2S-CLD-D24/8344355"]}, "item": null},
{"description_or_mfg_pn": "LC1D09BD", "supplier_links": {"sg.rs-online.com": ["https://sg.rs-online.com/web/p/contactors/3949807"], "sg.element14.com": ["https://sg.element14.com/schneider-electric/lc1d09bd/contactor-3pst-no-24vdc-din-rail/dp/2579146"]}, "item": null},
{"description_or_mfg_pn": "09330242701", "supplier_links": {"mouser.sg": ["https://www.mouser.sg/ProductDetail/HARTING/09330242701?qs=qa49y27LPCHF9XgrV2yw6A%3D%3D"], "digikey.sg": ["https://www.digikey.sg/en/products/detail/harting/09330242701/3180659"]}, "item": null},
{"description_or_mfg_pn": "SJ2S-05B", "supplier_links": {"mouser.sg": ["https://www.mouser.sg/ProductDetail/IDEC/SJ2S-05B?qs=LW8h5wBZGrF3eVXfMAs0ZQ%3D%3D"]}, "item": null},
{"description_or_mfg_pn": "3240264", "supplier_links": {"digikey.sg": ["https://www.digikey.sg/en/products/detail/phoenix-contact/3240264/2525024"], "mouser.sg": ["https://www.mouser.sg/ProductDetail/Phoenix-Contact/3240264?qs=GSRIBzA1BwzPwHaFPs6pEA%3D%3D"]}, "item": null},
{"description_or_mfg_pn": "RG316", "supplier_links": {}, "item": null},
{"description_or_mfg_pn": "EL8076-000", "supplier_links": {"mouser.sg": ["https://www.mouser.sg/ProductDetail/TE-Connectivity/EL8076-000?qs=sPbYRqrBIVl5%2FQnAcdDLrA%3D%3D"]}, "item": null}
]