[
{"mfg_pn": "3240294", "description": "Wire Duct Gray Solid (Raceway), 2 Piece Rivet 6.56' (2.00m)", "selling_length": 2.0, "url": "https://www.digikey.sg/en/products/detail/phoenix-contact/3240294/2525016", "pricing_table": [{"min_quantity": 1, "max_quantity": 9, "unit_price": 46.58}, {"min_quantity": 10, "max_quantity": 49, "unit_price": 43.54}, {"min_quantity": 50, "max_quantity": 99, "unit_price": 40.057}, {"min_quantity": 100, "max_quantity": 249, "unit_price": 37.0093}, {"min_quantity": 250, "max_quantity": 499, "unit_price": 35.26764}, {"min_quantity": 500, "max_quantity": 999999, "unit_price": 33.09084}], "delivery_days": {"min": 2, "max": 4}, "quantity_available": 460},
{"mfg_pn": "3240264", "description": "Wire Duct Gray Solid (Raceway), 2 Piece Rivet 6.56' (2.00m)", "selling_length": 2.0, "url": "https://www.digikey.sg/en/products/detail/phoenix-contact/3240264/2525024", "pricing_table": [{"min_quantity": 1, "max_quantity": 9, "unit_price": 56.59}, {"min_quantity": 10, "max_quantity": 49, "unit_price": 52.896}, {"min_quantity": 50, "max_quantity": 99, "unit_price": 48.6644}, {"min_quantity": 100, "max_quantity": 249, "unit_price": 44.9615}, {"min_quantity": 250, "max_quantity": 499, "unit_price": 42.84564}, {"min_quantity": 500, "max_quantity": 999999, "unit_price": 40.20092}], "delivery_days": {"min": 2, "max": 4}, "quantity_available": 1},
{"mfg_pn": "2002-1492", "description": "Connector End Plate For TOPJOB®S Series", "selling_length": null, "url": "https://www.digikey.sg/en/products/detail/wago-corporation/2002-1492/13549469", "pricing_table": [{"min_quantity": 1, "max_quantity": 9, "unit_price": 2.64}, {"min_quantity": 10, "max_quantity": 24, "unit_price": 2.305}, {"min_quantity": 25, "max_quantity": 49, "unit_price": 2.2072}, {"min_quantity": 50, "max_quantity": 99, "unit_price": 2.158}, {"min_quantity": 100, "max_quantity": 249, "unit_price": 2.0598}, {"min_quantity": 250, "max_quantity": 499, "unit_price": 1.86372}, {"min_quantity": 500, "max_quantity": 999, "unit_price": 1.71658}, {"min_quantity": 1000, "max_quantity": 2499, "unit_price": 1.47135}, {"min_quantity": 2500, "max_quantity": 999999, "unit_price": 1.37326}], "delivery_days": {"min": 2, "max": 4}, "quantity_available": 2628},
{"mfg_pn": "09330242701", "description": "Female Insert Gray 24+Ground Position Screw", "selling_length": null, "url": "https://www.digikey.sg/en/products/detail/harting/09330242701/3180659", "pricing_table": [{"min_quantity": 1, "max_quantity": 9, "unit_price": 45.29}, {"min_quantity": 10, "max_quantity": 24, "unit_price": 39.658}, {"min_quantity": 25, "max_quantity": 49, "unit_price": 37.944}, {"min_quantity": 50, "max_quantity": 99, "unit_price": 36.7204}, {"min_quantity": 100, "max_quantity": 249, "unit_price": 35.4963}, {"min_quantity": 250, "max_quantity": 999999, "unit_price": 33.53788}], "delivery_days": {"min": 2, "max": 4}, "quantity_available": 286},
{"mfg_pn": "RJ2S-CLD-D24", "description": "General Purpose Relay DPDT (2 Form C) 24VDC Coil Socketable", "selling_length": null, "url": "https://www.digikey.sg/en/products/detail/idec/RJ2S-CLD-D24/8344355", "pricing_table": [{"min_quantity": 1, "max_quantity": 9, "unit_price": 21.24}, {"min_quantity": 10, "max_quantity": 24, "unit_price": 18.874}, {"min_quantity": 25, "max_quantity": 49, "unit_price": 17.9312}, {"min_quantity": 50, "max_quantity": 99, "unit_price": 16.9872}, {"min_quantity": 100, "max_quantity": 249, "unit_price": 16.0435}, {"min_quantity": 250, "max_quantity": 499, "unit_price": 14.62784}, {"min_quantity": 500, "max_quantity": 999, "unit_price": 13.68412}, {"min_quantity": 1000, "max_quantity": 999999, "unit_price": 12.97632}], "delivery_days": {"min": 2, "max": 4}, "quantity_available": 270}
]